admin_client.py
ragflow_cli-0.23.1.dist-info/METADATA
ragflow_cli-0.23.1.dist-info/WHEEL
ragflow_cli-0.23.1.dist-info/entry_points.txt
ragflow_cli-0.23.1.dist-info/top_level.txt
ragflow_cli-0.23.1.dist-info/RECORD
