Metadata-Version: 2.4
Name: ragflow-cli
Version: 0.23.1
Summary: Admin Service's client of [RAGFlow](https://github.com/infiniflow/ragflow). The Admin Service provides user management and system monitoring. 
Author-email: Lynn <lynn_inf@hotmail.com>
License: Apache License, Version 2.0
Requires-Python: <3.15,>=3.12
Requires-Dist: requests<3.0.0,>=2.30.0
Requires-Dist: beartype<1.0.0,>=0.20.0
Requires-Dist: pycryptodomex>=3.10.0
Requires-Dist: lark>=1.1.0
